celery_mock/__init__.py
celery_mock/celery_mock.py
tests/__init__.py
tests/example_app.py
tests/test_celery_mock.py
celery_mock-1.1.7.dist-info/LICENSE
celery_mock-1.1.7.dist-info/WHEEL
celery_mock-1.1.7.dist-info/METADATA
celery_mock-1.1.7.dist-info/RECORD
