Metadata-Version: 2.1
Name: celery-mock
Version: 1.1.7
Summary: celery-mock allows you to mock celery task and run them when you want
Home-page: https://github.com/ulamlabs/celery-mock/
License: MIT
Keywords: celery,mock,celery_mock
Author: Konrad Rotkiewicz
Author-email: konrad@ulam.io
Requires-Python: >=3.6
Classifier: Development Status :: 5 - Production/Stable
Classifier: Intended Audience :: Developers
Classifier: License :: OSI Approved :: MIT License
Classifier: Natural Language :: English
Classifier: Programming Language :: Python :: 3
Classifier: Programming Language :: Python :: 3.6
Classifier: Programming Language :: Python :: 3.7
Classifier: Programming Language :: Python :: 3.8
Classifier: Programming Language :: Python :: 3.9
Requires-Dist: celery (>=4.0.0)
Project-URL: Repository, https://github.com/ulamlabs/celery-mock/
